Metadata-Version: 2.1
Name: pyion2json
Version: 0.0.1
Summary: Convert an Amazon Ion document(s) to JSON
Home-page: https://github.com/crouchcd/pyion2json
Author: crouchcd
Author-email: cdcsoftdev@gmail.com
License: MIT
Download-URL: https://github.com/crouchcd/pyion2json/archive/0.0.1.tar.gz
Keywords: Amazon,Ion,JSON
Platform: UNKNOWN
Classifier: Intended Audience :: Developers
Classifier: Topic :: Software Development :: Build Tools
Classifier: License :: OSI Approved :: MIT License
Classifier: Programming Language :: Python :: 3
